<annotation>
  <filename>000342.jpg</filename>
  <segmented>0</segmented>
  <size>
    <width>2171</width>
    <height>2138</height>
  </size>
  <object>
    <name>bed</name>
    <pose>Unspecified</pose>
    <truncated>0</truncated>
    <difficult>0</difficult>
    <bndbox>
      <xmin>419.511607</xmin>
      <ymin>711.910955</ymin>
      <xmax>637.873211</xmax>
      <ymax>1050.775358</ymax>
    </bndbox>
  </object>
  <object>
    <name>coffee_table</name>
    <pose>Unspecified</pose>
    <truncated>0</truncated>
    <difficult>0</difficult>
    <bndbox>
      <xmin>908.969296</xmin>
      <ymin>242.883324</ymin>
      <xmax>1084.075153</xmax>
      <ymax>418.331628</ymax>
    </bndbox>
  </object>
  <object>
    <name>small_sofa</name>
    <pose>Unspecified</pose>
    <truncated>0</truncated>
    <difficult>0</difficult>
    <bndbox>
      <xmin>196.844501</xmin>
      <ymin>144.361364</ymin>
      <xmax>516.537544</xmax>
      <ymax>461.242969</ymax>
    </bndbox>
  </object>
  <object>
    <name>tub</name>
    <pose>Unspecified</pose>
    <truncated>0</truncated>
    <difficult>0</difficult>
    <bndbox>
      <xmin>1633.519138</xmin>
      <ymin>393.751033</ymin>
      <xmax>2034.469984</xmax>
      <ymax>576.555257</ymax>
    </bndbox>
  </object>
  <object>
    <name>sink</name>
    <pose>Unspecified</pose>
    <truncated>0</truncated>
    <difficult>0</difficult>
    <bndbox>
      <xmin>1190.488511</xmin>
      <ymin>113.8973</ymin>
      <xmax>1468.685711</xmax>
      <ymax>253.4945</ymax>
    </bndbox>
  </object>
  <object>
    <name>large_sink</name>
    <pose>Unspecified</pose>
    <truncated>0</truncated>
    <difficult>0</difficult>
    <bndbox>
      <xmin>1846.487599</xmin>
      <ymin>113.665849</ymin>
      <xmax>2038.059756</xmax>
      <ymax>308.19461</ymax>
    </bndbox>
  </object>
  <object>
    <name>dining_table</name>
    <pose>Unspecified</pose>
    <truncated>0</truncated>
    <difficult>0</difficult>
    <bndbox>
      <xmin>1272.554716</xmin>
      <ymin>1309.618069</ymin>
      <xmax>1690.973885</xmax>
      <ymax>1726.353306</ymax>
    </bndbox>
  </object>
  <object>
    <name>large_sofa</name>
    <pose>Unspecified</pose>
    <truncated>0</truncated>
    <difficult>0</difficult>
    <bndbox>
      <xmin>354.146494</xmin>
      <ymin>1076.500984</ymin>
      <xmax>825.591694</xmax>
      <ymax>1274.230984</ymax>
    </bndbox>
  </object>
  <object>
    <name>coffee_table</name>
    <pose>Unspecified</pose>
    <truncated>0</truncated>
    <difficult>0</difficult>
    <bndbox>
      <xmin>550.063008</xmin>
      <ymin>1370.680387</ymin>
      <xmax>724.84317</xmax>
      <ymax>1545.41588</ymax>
    </bndbox>
  </object>
  <object>
    <name>small_sofa</name>
    <pose>Unspecified</pose>
    <truncated>0</truncated>
    <difficult>0</difficult>
    <bndbox>
      <xmin>187.218076</xmin>
      <ymin>1423.096888</ymin>
      <xmax>502.328153</xmax>
      <ymax>1730.950578</ymax>
    </bndbox>
  </object>
  <object>
    <name>small_sofa</name>
    <pose>Unspecified</pose>
    <truncated>0</truncated>
    <difficult>0</difficult>
    <bndbox>
      <xmin>833.944943</xmin>
      <ymin>1416.266582</ymin>
      <xmax>1131.019711</xmax>
      <ymax>1699.708684</ymax>
    </bndbox>
  </object>
  <object>
    <name>coffee_table</name>
    <pose>Unspecified</pose>
    <truncated>0</truncated>
    <difficult>0</difficult>
    <bndbox>
      <xmin>1815.166022</xmin>
      <ymin>1716.679494</ymin>
      <xmax>2055.664022</xmax>
      <ymax>1956.702294</ymax>
    </bndbox>
  </object>
  <object>
    <name>small_sofa</name>
    <pose>Unspecified</pose>
    <truncated>0</truncated>
    <difficult>0</difficult>
    <bndbox>
      <xmin>1796.007056</xmin>
      <ymin>812.834323</ymin>
      <xmax>2012.745056</xmax>
      <ymax>1052.381923</ymax>
    </bndbox>
  </object>
  <object>
    <name>coffee_table</name>
    <pose>Unspecified</pose>
    <truncated>0</truncated>
    <difficult>0</difficult>
    <bndbox>
      <xmin>1662.824423</xmin>
      <ymin>600.52487</ymin>
      <xmax>1836.906988</xmax>
      <ymax>774.947786</ymax>
    </bndbox>
  </object>
  <object>
    <name>coffee_table</name>
    <pose>Unspecified</pose>
    <truncated>0</truncated>
    <difficult>0</difficult>
    <bndbox>
      <xmin>1828.830438</xmin>
      <ymin>600.258722</ymin>
      <xmax>2002.913003</xmax>
      <ymax>774.681638</ymax>
    </bndbox>
  </object>
  <object>
    <name>coffee_table</name>
    <pose>Unspecified</pose>
    <truncated>0</truncated>
    <difficult>0</difficult>
    <bndbox>
      <xmin>1497.405478</xmin>
      <ymin>600.111558</ymin>
      <xmax>1671.488042</xmax>
      <ymax>774.534474</ymax>
    </bndbox>
  </object>
  <object>
    <name>coffee_table</name>
    <pose>Unspecified</pose>
    <truncated>0</truncated>
    <difficult>0</difficult>
    <bndbox>
      <xmin>1882.387609</xmin>
      <ymin>1073.073492</ymin>
      <xmax>2056.470174</xmax>
      <ymax>1247.496408</ymax>
    </bndbox>
  </object>
  <object>
    <name>twin_sink</name>
    <pose>Unspecified</pose>
    <truncated>0</truncated>
    <difficult>0</difficult>
    <bndbox>
      <xmin>1911.07535</xmin>
      <ymin>1243.540778</ymin>
      <xmax>2055.945632</xmax>
      <ymax>1648.695398</ymax>
    </bndbox>
  </object>
</annotation>
