<annotation>
  <filename>000905.jpg</filename>
  <segmented>0</segmented>
  <size>
    <width>4349</width>
    <height>2227</height>
  </size>
  <object>
    <name>large_sink</name>
    <pose>Unspecified</pose>
    <truncated>0</truncated>
    <difficult>0</difficult>
    <bndbox>
      <xmin>2551.439966</xmin>
      <ymin>1659.51438</ymin>
      <xmax>2748.896966</xmax>
      <ymax>1853.79938</ymax>
    </bndbox>
  </object>
  <object>
    <name>small_sofa</name>
    <pose>Unspecified</pose>
    <truncated>0</truncated>
    <difficult>0</difficult>
    <bndbox>
      <xmin>3273.387664</xmin>
      <ymin>1431.979407</ymin>
      <xmax>3553.869194</xmax>
      <ymax>1727.249522</ymax>
    </bndbox>
  </object>
  <object>
    <name>small_sofa</name>
    <pose>Unspecified</pose>
    <truncated>0</truncated>
    <difficult>0</difficult>
    <bndbox>
      <xmin>3043.510654</xmin>
      <ymin>533.618699</ymin>
      <xmax>3326.354649</xmax>
      <ymax>799.203985</ymax>
    </bndbox>
  </object>
  <object>
    <name>small_sink</name>
    <pose>Unspecified</pose>
    <truncated>0</truncated>
    <difficult>0</difficult>
    <bndbox>
      <xmin>2593.58088</xmin>
      <ymin>1363.24467</ymin>
      <xmax>2747.819377</xmax>
      <ymax>1561.494663</ymax>
    </bndbox>
  </object>
  <object>
    <name>twin_sink</name>
    <pose>Unspecified</pose>
    <truncated>0</truncated>
    <difficult>0</difficult>
    <bndbox>
      <xmin>3443.585787</xmin>
      <ymin>515.248486</ymin>
      <xmax>3987.135884</xmax>
      <ymax>709.634578</ymax>
    </bndbox>
  </object>
  <object>
    <name>dining_table</name>
    <pose>Unspecified</pose>
    <truncated>0</truncated>
    <difficult>0</difficult>
    <bndbox>
      <xmin>1748.341384</xmin>
      <ymin>402.715004</ymin>
      <xmax>2105.984384</xmax>
      <ymax>806.352004</ymax>
    </bndbox>
  </object>
  <object>
    <name>large_sofa</name>
    <pose>Unspecified</pose>
    <truncated>0</truncated>
    <difficult>0</difficult>
    <bndbox>
      <xmin>191.449578</xmin>
      <ymin>182.48607</ymin>
      <xmax>666.139378</xmax>
      <ymax>383.11507</ymax>
    </bndbox>
  </object>
  <object>
    <name>small_sofa</name>
    <pose>Unspecified</pose>
    <truncated>0</truncated>
    <difficult>0</difficult>
    <bndbox>
      <xmin>193.510794</xmin>
      <ymin>587.819983</ymin>
      <xmax>508.243229</xmax>
      <ymax>908.271971</ymax>
    </bndbox>
  </object>
  <object>
    <name>coffee_table</name>
    <pose>Unspecified</pose>
    <truncated>0</truncated>
    <difficult>0</difficult>
    <bndbox>
      <xmin>2522.671842</xmin>
      <ymin>1130.331983</ymin>
      <xmax>2730.510046</xmax>
      <ymax>1337.677306</ymax>
    </bndbox>
  </object>
  <object>
    <name>coffee_table</name>
    <pose>Unspecified</pose>
    <truncated>0</truncated>
    <difficult>0</difficult>
    <bndbox>
      <xmin>191.963328</xmin>
      <ymin>1017.113552</ymin>
      <xmax>399.475606</xmax>
      <ymax>1225.061327</ymax>
    </bndbox>
  </object>
  <object>
    <name>coffee_table</name>
    <pose>Unspecified</pose>
    <truncated>0</truncated>
    <difficult>0</difficult>
    <bndbox>
      <xmin>2789.460407</xmin>
      <ymin>1647.698274</ymin>
      <xmax>2994.896506</xmax>
      <ymax>1853.533408</ymax>
    </bndbox>
  </object>
  <object>
    <name>small_sofa</name>
    <pose>Unspecified</pose>
    <truncated>0</truncated>
    <difficult>0</difficult>
    <bndbox>
      <xmin>3005.250542</xmin>
      <ymin>904.202472</ymin>
      <xmax>3324.565013</xmax>
      <ymax>1216.967246</ymax>
    </bndbox>
  </object>
  <object>
    <name>small_sofa</name>
    <pose>Unspecified</pose>
    <truncated>0</truncated>
    <difficult>0</difficult>
    <bndbox>
      <xmin>1400.051834</xmin>
      <ymin>1531.783094</ymin>
      <xmax>1719.59324</xmax>
      <ymax>1854.420166</ymax>
    </bndbox>
  </object>
</annotation>
