<annotation>
  <filename>000973.jpg</filename>
  <segmented>0</segmented>
  <size>
    <width>4349</width>
    <height>2227</height>
  </size>
  <object>
    <name>large_sink</name>
    <pose>Unspecified</pose>
    <truncated>0</truncated>
    <difficult>0</difficult>
    <bndbox>
      <xmin>2551.439966</xmin>
      <ymin>1659.51438</ymin>
      <xmax>2748.896966</xmax>
      <ymax>1853.79938</ymax>
    </bndbox>
  </object>
  <object>
    <name>armchair</name>
    <pose>Unspecified</pose>
    <truncated>0</truncated>
    <difficult>0</difficult>
    <bndbox>
      <xmin>3042.934289</xmin>
      <ymin>533.618699</ymin>
      <xmax>3326.354649</xmax>
      <ymax>824.524811</ymax>
    </bndbox>
  </object>
  <object>
    <name>small_sink</name>
    <pose>Unspecified</pose>
    <truncated>0</truncated>
    <difficult>0</difficult>
    <bndbox>
      <xmin>2593.58088</xmin>
      <ymin>1363.24467</ymin>
      <xmax>2747.819377</xmax>
      <ymax>1561.494663</ymax>
    </bndbox>
  </object>
  <object>
    <name>sink</name>
    <pose>Unspecified</pose>
    <truncated>0</truncated>
    <difficult>0</difficult>
    <bndbox>
      <xmin>3521.164003</xmin>
      <ymin>515.248486</ymin>
      <xmax>3907.990919</xmax>
      <ymax>709.187126</ymax>
    </bndbox>
  </object>
  <object>
    <name>round_table</name>
    <pose>Unspecified</pose>
    <truncated>0</truncated>
    <difficult>0</difficult>
    <bndbox>
      <xmin>1728.4633</xmin>
      <ymin>369.091804</ymin>
      <xmax>2200.2983</xmax>
      <ymax>839.975204</ymax>
    </bndbox>
  </object>
  <object>
    <name>large_sofa</name>
    <pose>Unspecified</pose>
    <truncated>0</truncated>
    <difficult>0</difficult>
    <bndbox>
      <xmin>191.449578</xmin>
      <ymin>182.48607</ymin>
      <xmax>666.139378</xmax>
      <ymax>383.11507</ymax>
    </bndbox>
  </object>
  <object>
    <name>armchair</name>
    <pose>Unspecified</pose>
    <truncated>0</truncated>
    <difficult>0</difficult>
    <bndbox>
      <xmin>193.510791</xmin>
      <ymin>619.218726</ymin>
      <xmax>491.532892</xmax>
      <ymax>908.271968</ymax>
    </bndbox>
  </object>
  <object>
    <name>coffee_table</name>
    <pose>Unspecified</pose>
    <truncated>0</truncated>
    <difficult>0</difficult>
    <bndbox>
      <xmin>2895.509594</xmin>
      <ymin>1648.853285</ymin>
      <xmax>3100.945693</xmax>
      <ymax>1854.688418</ymax>
    </bndbox>
  </object>
  <object>
    <name>armchair</name>
    <pose>Unspecified</pose>
    <truncated>0</truncated>
    <difficult>0</difficult>
    <bndbox>
      <xmin>3305.947349</xmin>
      <ymin>1452.384727</ymin>
      <xmax>3586.314523</xmax>
      <ymax>1727.249522</ymax>
    </bndbox>
  </object>
  <object>
    <name>coffee_table</name>
    <pose>Unspecified</pose>
    <truncated>0</truncated>
    <difficult>0</difficult>
    <bndbox>
      <xmin>2522.797453</xmin>
      <ymin>1130.494964</ymin>
      <xmax>2730.510052</xmax>
      <ymax>1337.677306</ymax>
    </bndbox>
  </object>
  <object>
    <name>armchair</name>
    <pose>Unspecified</pose>
    <truncated>0</truncated>
    <difficult>0</difficult>
    <bndbox>
      <xmin>3009.993738</xmin>
      <ymin>913.593822</ymin>
      <xmax>3324.56501</xmax>
      <ymax>1216.967246</ymax>
    </bndbox>
  </object>
  <object>
    <name>armchair</name>
    <pose>Unspecified</pose>
    <truncated>0</truncated>
    <difficult>0</difficult>
    <bndbox>
      <xmin>1400.051834</xmin>
      <ymin>1533.135664</ymin>
      <xmax>1713.617503</xmax>
      <ymax>1854.420166</ymax>
    </bndbox>
  </object>
</annotation>
