<annotation>
	<folder>Robin_regions</folder>
	<filename>Cat8_2.jpg</filename>
	<path>/media/matrix/Data/BRIDGE/Robin_regions/Cat8_2.jpg</path>
	<source>
		<database>Unknown</database>
	</source>
	<size>
		<width>946</width>
		<height>1425</height>
		<depth>1</depth>
	</size>
	<segmented>0</segmented>
	<object>
		<name>bathroom has tubs, large sink</name>
		<pose>Unspecified</pose>
		<truncated>0</truncated>
		<difficult>0</difficult>
		<bndbox>
			<xmin>9</xmin>
			<ymin>12</ymin>
			<xmax>367</xmax>
			<ymax>478</ymax>
		</bndbox>
	</object>
	<object>
		<name>kitchen has dining table and sink</name>
		<pose>Unspecified</pose>
		<truncated>0</truncated>
		<difficult>0</difficult>
		<bndbox>
			<xmin>376</xmin>
			<ymin>6</ymin>
			<xmax>842</xmax>
			<ymax>472</ymax>
		</bndbox>
	</object>
	<object>
		<name>living room has a large sofa and coffee table</name>
		<pose>Unspecified</pose>
		<truncated>0</truncated>
		<difficult>0</difficult>
		<bndbox>
			<xmin>2</xmin>
			<ymin>478</ymin>
			<xmax>479</xmax>
			<ymax>1411</ymax>
		</bndbox>
	</object>
	<object>
		<name>bedroom has a single bed and small sofa</name>
		<pose>Unspecified</pose>
		<truncated>0</truncated>
		<difficult>0</difficult>
		<bndbox>
			<xmin>479</xmin>
			<ymin>947</ymin>
			<xmax>820</xmax>
			<ymax>1420</ymax>
		</bndbox>
	</object>
</annotation>
