<annotation>
	<folder>train_images_temp</folder>
	<filename>Cat28_6.jpg</filename>
	<path>/home/shreya/BTP_deewan_harshit/darkflow-master/dataset/train_images_temp/Cat28_6.jpg</path>
	<source>
		<database>Unknown</database>
	</source>
	<size>
		<width>1178</width>
		<height>1265</height>
		<depth>1</depth>
	</size>
	<segmented>0</segmented>
	<object>
		<name>dining_table</name>
		<pose>Unspecified</pose>
		<truncated>0</truncated>
		<difficult>0</difficult>
		<bndbox>
			<xmin>452</xmin>
			<ymin>125</ymin>
			<xmax>639</xmax>
			<ymax>347</ymax>
		</bndbox>
	</object>
	<object>
		<name>coffee_table</name>
		<pose>Unspecified</pose>
		<truncated>0</truncated>
		<difficult>0</difficult>
		<bndbox>
			<xmin>260</xmin>
			<ymin>278</ymin>
			<xmax>376</xmax>
			<ymax>386</ymax>
		</bndbox>
	</object>
	<object>
		<name>bed</name>
		<pose>Unspecified</pose>
		<truncated>0</truncated>
		<difficult>0</difficult>
		<bndbox>
			<xmin>235</xmin>
			<ymin>22</ymin>
			<xmax>363</xmax>
			<ymax>205</ymax>
		</bndbox>
	</object>
	<object>
		<name>tub</name>
		<pose>Unspecified</pose>
		<truncated>0</truncated>
		<difficult>0</difficult>
		<bndbox>
			<xmin>736</xmin>
			<ymin>46</ymin>
			<xmax>935</xmax>
			<ymax>137</ymax>
		</bndbox>
	</object>
	<object>
		<name>large_sink</name>
		<pose>Unspecified</pose>
		<truncated>0</truncated>
		<difficult>0</difficult>
		<bndbox>
			<xmin>728</xmin>
			<ymin>301</ymin>
			<xmax>815</xmax>
			<ymax>386</ymax>
		</bndbox>
	</object>
	<object>
		<name>large_sofa</name>
		<pose>Unspecified</pose>
		<truncated>0</truncated>
		<difficult>0</difficult>
		<bndbox>
			<xmin>74</xmin>
			<ymin>547</ymin>
			<xmax>195</xmax>
			<ymax>802</ymax>
		</bndbox>
	</object>
	<object>
		<name>round_table</name>
		<pose>Unspecified</pose>
		<truncated>0</truncated>
		<difficult>0</difficult>
		<bndbox>
			<xmin>226</xmin>
			<ymin>567</ymin>
			<xmax>363</xmax>
			<ymax>707</ymax>
		</bndbox>
	</object>
	<object>
		<name>coffee_table</name>
		<pose>Unspecified</pose>
		<truncated>0</truncated>
		<difficult>0</difficult>
		<bndbox>
			<xmin>904</xmin>
			<ymin>614</ymin>
			<xmax>1015</xmax>
			<ymax>721</ymax>
		</bndbox>
	</object>
	<object>
		<name>twin_sink</name>
		<pose>Unspecified</pose>
		<truncated>0</truncated>
		<difficult>0</difficult>
		<bndbox>
			<xmin>1065</xmin>
			<ymin>642</ymin>
			<xmax>1137</xmax>
			<ymax>795</ymax>
		</bndbox>
	</object>
	<object>
		<name>small_sofa</name>
		<pose>Unspecified</pose>
		<truncated>0</truncated>
		<difficult>0</difficult>
		<bndbox>
			<xmin>347</xmin>
			<ymin>874</ymin>
			<xmax>472</xmax>
			<ymax>986</ymax>
		</bndbox>
	</object>
	<object>
		<name>small_sofa</name>
		<pose>Unspecified</pose>
		<truncated>0</truncated>
		<difficult>0</difficult>
		<bndbox>
			<xmin>349</xmin>
			<ymin>1015</ymin>
			<xmax>472</xmax>
			<ymax>1122</ymax>
		</bndbox>
	</object>
	<object>
		<name>coffee_table</name>
		<pose>Unspecified</pose>
		<truncated>0</truncated>
		<difficult>0</difficult>
		<bndbox>
			<xmin>869</xmin>
			<ymin>942</ymin>
			<xmax>979</xmax>
			<ymax>1051</ymax>
		</bndbox>
	</object>
	<object>
		<name>large_sofa</name>
		<pose>Unspecified</pose>
		<truncated>0</truncated>
		<difficult>0</difficult>
		<bndbox>
			<xmin>1007</xmin>
			<ymin>868</ymin>
			<xmax>1131</xmax>
			<ymax>1121</ymax>
		</bndbox>
	</object>
</annotation>