<annotation>
	<folder>train_images_temp</folder>
	<filename>Cat30_7.jpg</filename>
	<path>/home/shreya/BTP_deewan_harshit/darkflow-master/dataset/train_images_temp/Cat30_7.jpg</path>
	<source>
		<database>Unknown</database>
	</source>
	<size>
		<width>1266</width>
		<height>1179</height>
		<depth>1</depth>
	</size>
	<segmented>0</segmented>
	<object>
		<name>large_sofa</name>
		<pose>Unspecified</pose>
		<truncated>0</truncated>
		<difficult>0</difficult>
		<bndbox>
			<xmin>141</xmin>
			<ymin>53</ymin>
			<xmax>396</xmax>
			<ymax>163</ymax>
		</bndbox>
	</object>
	<object>
		<name>coffee_table</name>
		<pose>Unspecified</pose>
		<truncated>0</truncated>
		<difficult>0</difficult>
		<bndbox>
			<xmin>212</xmin>
			<ymin>198</ymin>
			<xmax>326</xmax>
			<ymax>310</ymax>
		</bndbox>
	</object>
	<object>
		<name>small_sofa</name>
		<pose>Unspecified</pose>
		<truncated>0</truncated>
		<difficult>0</difficult>
		<bndbox>
			<xmin>142</xmin>
			<ymin>704</ymin>
			<xmax>254</xmax>
			<ymax>827</ymax>
		</bndbox>
	</object>
	<object>
		<name>small_sofa</name>
		<pose>Unspecified</pose>
		<truncated>0</truncated>
		<difficult>0</difficult>
		<bndbox>
			<xmin>277</xmin>
			<ymin>707</ymin>
			<xmax>387</xmax>
			<ymax>827</ymax>
		</bndbox>
	</object>
	<object>
		<name>coffee_table</name>
		<pose>Unspecified</pose>
		<truncated>0</truncated>
		<difficult>0</difficult>
		<bndbox>
			<xmin>545</xmin>
			<ymin>164</ymin>
			<xmax>659</xmax>
			<ymax>271</ymax>
		</bndbox>
	</object>
	<object>
		<name>twin_sink</name>
		<pose>Unspecified</pose>
		<truncated>0</truncated>
		<difficult>0</difficult>
		<bndbox>
			<xmin>467</xmin>
			<ymin>49</ymin>
			<xmax>625</xmax>
			<ymax>114</ymax>
		</bndbox>
	</object>
	<object>
		<name>round_table</name>
		<pose>Unspecified</pose>
		<truncated>0</truncated>
		<difficult>0</difficult>
		<bndbox>
			<xmin>558</xmin>
			<ymin>810</ymin>
			<xmax>692</xmax>
			<ymax>953</ymax>
		</bndbox>
	</object>
	<object>
		<name>large_sofa</name>
		<pose>Unspecified</pose>
		<truncated>0</truncated>
		<difficult>0</difficult>
		<bndbox>
			<xmin>468</xmin>
			<ymin>988</ymin>
			<xmax>726</xmax>
			<ymax>1107</ymax>
		</bndbox>
	</object>
	<object>
		<name>bed</name>
		<pose>Unspecified</pose>
		<truncated>0</truncated>
		<difficult>0</difficult>
		<bndbox>
			<xmin>994</xmin>
			<ymin>242</ymin>
			<xmax>1177</xmax>
			<ymax>371</ymax>
		</bndbox>
	</object>
	<object>
		<name>bed</name>
		<pose>Unspecified</pose>
		<truncated>0</truncated>
		<difficult>0</difficult>
		<bndbox>
			<xmin>999</xmin>
			<ymin>496</ymin>
			<xmax>1195</xmax>
			<ymax>624</ymax>
		</bndbox>
	</object>
	<object>
		<name>coffee_table</name>
		<pose>Unspecified</pose>
		<truncated>0</truncated>
		<difficult>0</difficult>
		<bndbox>
			<xmin>800</xmin>
			<ymin>517</ymin>
			<xmax>911</xmax>
			<ymax>626</ymax>
		</bndbox>
	</object>
	<object>
		<name>large_sink</name>
		<pose>Unspecified</pose>
		<truncated>0</truncated>
		<difficult>0</difficult>
		<bndbox>
			<xmin>804</xmin>
			<ymin>740</ymin>
			<xmax>894</xmax>
			<ymax>826</ymax>
		</bndbox>
	</object>
	<object>
		<name>tub</name>
		<pose>Unspecified</pose>
		<truncated>0</truncated>
		<difficult>0</difficult>
		<bndbox>
			<xmin>1126</xmin>
			<ymin>757</ymin>
			<xmax>1223</xmax>
			<ymax>942</ymax>
		</bndbox>
	</object>
</annotation>