<annotation>
	<folder>D2_new</folder>
	<filename>231812.jpeg</filename>
	<path>/media/matrix/Data/data_new/D2_new/231812.jpeg</path>
	<source>
		<database>Unknown</database>
	</source>
	<size>
		<width>0</width>
		<height>0</height>
		<depth>3</depth>
	</size>
	<segmented>0</segmented>
	<object>
		<name>stairs</name>
		<pose>Unspecified</pose>
		<truncated>0</truncated>
		<difficult>0</difficult>
		<bndbox>
			<xmin>292</xmin>
			<ymin>268</ymin>
			<xmax>530</xmax>
			<ymax>328</ymax>
		</bndbox>
	</object>
	<object>
		<name>door</name>
		<pose>Unspecified</pose>
		<truncated>0</truncated>
		<difficult>0</difficult>
		<bndbox>
			<xmin>498</xmin>
			<ymin>226</ymin>
			<xmax>543</xmax>
			<ymax>271</ymax>
		</bndbox>
	</object>
	<object>
		<name>door</name>
		<pose>Unspecified</pose>
		<truncated>0</truncated>
		<difficult>0</difficult>
		<bndbox>
			<xmin>569</xmin>
			<ymin>267</ymin>
			<xmax>612</xmax>
			<ymax>314</ymax>
		</bndbox>
	</object>
	<object>
		<name>door</name>
		<pose>Unspecified</pose>
		<truncated>0</truncated>
		<difficult>0</difficult>
		<bndbox>
			<xmin>410</xmin>
			<ymin>377</ymin>
			<xmax>470</xmax>
			<ymax>427</ymax>
		</bndbox>
	</object>
	<object>
		<name>door</name>
		<pose>Unspecified</pose>
		<truncated>0</truncated>
		<difficult>0</difficult>
		<bndbox>
			<xmin>541</xmin>
			<ymin>374</ymin>
			<xmax>594</xmax>
			<ymax>425</ymax>
		</bndbox>
	</object>
	<object>
		<name>door</name>
		<pose>Unspecified</pose>
		<truncated>0</truncated>
		<difficult>0</difficult>
		<bndbox>
			<xmin>409</xmin>
			<ymin>429</ymin>
			<xmax>471</xmax>
			<ymax>476</ymax>
		</bndbox>
	</object>
	<object>
		<name>door</name>
		<pose>Unspecified</pose>
		<truncated>0</truncated>
		<difficult>0</difficult>
		<bndbox>
			<xmin>482</xmin>
			<ymin>462</ymin>
			<xmax>527</xmax>
			<ymax>514</ymax>
		</bndbox>
	</object>
	<object>
		<name>door</name>
		<pose>Unspecified</pose>
		<truncated>0</truncated>
		<difficult>0</difficult>
		<bndbox>
			<xmin>510</xmin>
			<ymin>428</ymin>
			<xmax>548</xmax>
			<ymax>464</ymax>
		</bndbox>
	</object>
	<object>
		<name>tub</name>
		<pose>Unspecified</pose>
		<truncated>0</truncated>
		<difficult>0</difficult>
		<bndbox>
			<xmin>292</xmin>
			<ymin>339</ymin>
			<xmax>347</xmax>
			<ymax>429</ymax>
		</bndbox>
	</object>
	<object>
		<name>large_sink</name>
		<pose>Unspecified</pose>
		<truncated>0</truncated>
		<difficult>0</difficult>
		<bndbox>
			<xmin>353</xmin>
			<ymin>324</ymin>
			<xmax>392</xmax>
			<ymax>369</ymax>
		</bndbox>
	</object>
	<object>
		<name>small_sink</name>
		<pose>Unspecified</pose>
		<truncated>0</truncated>
		<difficult>0</difficult>
		<bndbox>
			<xmin>394</xmin>
			<ymin>324</ymin>
			<xmax>473</xmax>
			<ymax>364</ymax>
		</bndbox>
	</object>
	<object>
		<name>window</name>
		<pose>Unspecified</pose>
		<truncated>0</truncated>
		<difficult>0</difficult>
		<bndbox>
			<xmin>457</xmin>
			<ymin>30</ymin>
			<xmax>539</xmax>
			<ymax>53</ymax>
		</bndbox>
	</object>
	<object>
		<name>window</name>
		<pose>Unspecified</pose>
		<truncated>0</truncated>
		<difficult>0</difficult>
		<bndbox>
			<xmin>320</xmin>
			<ymin>637</ymin>
			<xmax>366</xmax>
			<ymax>660</ymax>
		</bndbox>
	</object>
	<object>
		<name>window</name>
		<pose>Unspecified</pose>
		<truncated>0</truncated>
		<difficult>0</difficult>
		<bndbox>
			<xmin>420</xmin>
			<ymin>638</ymin>
			<xmax>467</xmax>
			<ymax>660</ymax>
		</bndbox>
	</object>
	<object>
		<name>window</name>
		<pose>Unspecified</pose>
		<truncated>0</truncated>
		<difficult>0</difficult>
		<bndbox>
			<xmin>523</xmin>
			<ymin>640</ymin>
			<xmax>570</xmax>
			<ymax>660</ymax>
		</bndbox>
	</object>
	<object>
		<name>window</name>
		<pose>Unspecified</pose>
		<truncated>0</truncated>
		<difficult>0</difficult>
		<bndbox>
			<xmin>750</xmin>
			<ymin>778</ymin>
			<xmax>797</xmax>
			<ymax>794</ymax>
		</bndbox>
	</object>
</annotation>
