<annotation>
	<folder>D2_new</folder>
	<filename>24561.jpeg</filename>
	<path>C:/Users/CC/Downloads/Radhika/D2_new/24561.jpeg</path>
	<source>
		<database>Unknown</database>
	</source>
	<size>
		<width>1024</width>
		<height>1975</height>
		<depth>1</depth>
	</size>
	<segmented>0</segmented>
	<object>
		<name>door</name>
		<pose>Unspecified</pose>
		<truncated>0</truncated>
		<difficult>0</difficult>
		<bndbox>
			<xmin>532</xmin>
			<ymin>926</ymin>
			<xmax>594</xmax>
			<ymax>1011</ymax>
		</bndbox>
	</object>
	<object>
		<name>door</name>
		<pose>Unspecified</pose>
		<truncated>0</truncated>
		<difficult>0</difficult>
		<bndbox>
			<xmin>335</xmin>
			<ymin>773</ymin>
			<xmax>423</xmax>
			<ymax>826</ymax>
		</bndbox>
	</object>
	<object>
		<name>door</name>
		<pose>Unspecified</pose>
		<truncated>0</truncated>
		<difficult>0</difficult>
		<bndbox>
			<xmin>373</xmin>
			<ymin>511</ymin>
			<xmax>469</xmax>
			<ymax>598</ymax>
		</bndbox>
	</object>
	<object>
		<name>door</name>
		<pose>Unspecified</pose>
		<truncated>0</truncated>
		<difficult>0</difficult>
		<bndbox>
			<xmin>538</xmin>
			<ymin>658</ymin>
			<xmax>626</xmax>
			<ymax>726</ymax>
		</bndbox>
	</object>
	<object>
		<name>door</name>
		<pose>Unspecified</pose>
		<truncated>0</truncated>
		<difficult>0</difficult>
		<bndbox>
			<xmin>698</xmin>
			<ymin>733</ymin>
			<xmax>744</xmax>
			<ymax>814</ymax>
		</bndbox>
	</object>
	<object>
		<name>door</name>
		<pose>Unspecified</pose>
		<truncated>0</truncated>
		<difficult>0</difficult>
		<bndbox>
			<xmin>735</xmin>
			<ymin>751</ymin>
			<xmax>810</xmax>
			<ymax>826</ymax>
		</bndbox>
	</object>
	<object>
		<name>door</name>
		<pose>Unspecified</pose>
		<truncated>0</truncated>
		<difficult>0</difficult>
		<bndbox>
			<xmin>644</xmin>
			<ymin>1164</ymin>
			<xmax>704</xmax>
			<ymax>1261</ymax>
		</bndbox>
	</object>
	<object>
		<name>door</name>
		<pose>Unspecified</pose>
		<truncated>0</truncated>
		<difficult>0</difficult>
		<bndbox>
			<xmin>588</xmin>
			<ymin>1329</ymin>
			<xmax>676</xmax>
			<ymax>1383</ymax>
		</bndbox>
	</object>
	<object>
		<name>door</name>
		<pose>Unspecified</pose>
		<truncated>0</truncated>
		<difficult>0</difficult>
		<bndbox>
			<xmin>601</xmin>
			<ymin>1489</ymin>
			<xmax>691</xmax>
			<ymax>1545</ymax>
		</bndbox>
	</object>
	<object>
		<name>door</name>
		<pose>Unspecified</pose>
		<truncated>0</truncated>
		<difficult>0</difficult>
		<bndbox>
			<xmin>641</xmin>
			<ymin>1614</ymin>
			<xmax>716</xmax>
			<ymax>1733</ymax>
		</bndbox>
	</object>
	<object>
		<name>door</name>
		<pose>Unspecified</pose>
		<truncated>0</truncated>
		<difficult>0</difficult>
		<bndbox>
			<xmin>479</xmin>
			<ymin>1689</ymin>
			<xmax>554</xmax>
			<ymax>1761</ymax>
		</bndbox>
	</object>
	<object>
		<name>door</name>
		<pose>Unspecified</pose>
		<truncated>0</truncated>
		<difficult>0</difficult>
		<bndbox>
			<xmin>669</xmin>
			<ymin>1439</ymin>
			<xmax>716</xmax>
			<ymax>1492</ymax>
		</bndbox>
	</object>
	<object>
		<name>door</name>
		<pose>Unspecified</pose>
		<truncated>0</truncated>
		<difficult>0</difficult>
		<bndbox>
			<xmin>763</xmin>
			<ymin>1439</ymin>
			<xmax>819</xmax>
			<ymax>1498</ymax>
		</bndbox>
	</object>
	<object>
		<name>door</name>
		<pose>Unspecified</pose>
		<truncated>0</truncated>
		<difficult>0</difficult>
		<bndbox>
			<xmin>448</xmin>
			<ymin>1001</ymin>
			<xmax>523</xmax>
			<ymax>1051</ymax>
		</bndbox>
	</object>
	<object>
		<name>twin_sink</name>
		<pose>Unspecified</pose>
		<truncated>0</truncated>
		<difficult>0</difficult>
		<bndbox>
			<xmin>98</xmin>
			<ymin>879</ymin>
			<xmax>210</xmax>
			<ymax>954</ymax>
		</bndbox>
	</object>
	<object>
		<name>small_sink</name>
		<pose>Unspecified</pose>
		<truncated>0</truncated>
		<difficult>0</difficult>
		<bndbox>
			<xmin>604</xmin>
			<ymin>598</ymin>
			<xmax>701</xmax>
			<ymax>651</ymax>
		</bndbox>
	</object>
	<object>
		<name>small_sink</name>
		<pose>Unspecified</pose>
		<truncated>0</truncated>
		<difficult>0</difficult>
		<bndbox>
			<xmin>835</xmin>
			<ymin>601</ymin>
			<xmax>938</xmax>
			<ymax>658</ymax>
		</bndbox>
	</object>
	<object>
		<name>large_sink</name>
		<pose>Unspecified</pose>
		<truncated>0</truncated>
		<difficult>0</difficult>
		<bndbox>
			<xmin>598</xmin>
			<ymin>733</ymin>
			<xmax>685</xmax>
			<ymax>854</ymax>
		</bndbox>
	</object>
	<object>
		<name>window</name>
		<pose>Unspecified</pose>
		<truncated>0</truncated>
		<difficult>0</difficult>
		<bndbox>
			<xmin>60</xmin>
			<ymin>1117</ymin>
			<xmax>126</xmax>
			<ymax>1392</ymax>
		</bndbox>
	</object>
	<object>
		<name>tub</name>
		<pose>Unspecified</pose>
		<truncated>0</truncated>
		<difficult>0</difficult>
		<bndbox>
			<xmin>857</xmin>
			<ymin>1373</ymin>
			<xmax>929</xmax>
			<ymax>1489</ymax>
		</bndbox>
	</object>
	<object>
		<name>large_sink</name>
		<pose>Unspecified</pose>
		<truncated>0</truncated>
		<difficult>0</difficult>
		<bndbox>
			<xmin>785</xmin>
			<ymin>1376</ymin>
			<xmax>857</xmax>
			<ymax>1448</ymax>
		</bndbox>
	</object>
	<object>
		<name>small_sink</name>
		<pose>Unspecified</pose>
		<truncated>0</truncated>
		<difficult>0</difficult>
		<bndbox>
			<xmin>676</xmin>
			<ymin>1376</ymin>
			<xmax>791</xmax>
			<ymax>1426</ymax>
		</bndbox>
	</object>
</annotation>
