<annotation>
	<folder>D2_new</folder>
	<filename>28411.jpeg</filename>
	<path>E:/doc/Radhika/D2_new/28411.jpeg</path>
	<source>
		<database>Unknown</database>
	</source>
	<size>
		<width>0</width>
		<height>0</height>
		<depth>3</depth>
	</size>
	<segmented>0</segmented>
	<object>
		<name>stairs</name>
		<pose>Unspecified</pose>
		<truncated>0</truncated>
		<difficult>0</difficult>
		<bndbox>
			<xmin>526</xmin>
			<ymin>353</ymin>
			<xmax>642</xmax>
			<ymax>499</ymax>
		</bndbox>
	</object>
	<object>
		<name>stairs</name>
		<pose>Unspecified</pose>
		<truncated>0</truncated>
		<difficult>0</difficult>
		<bndbox>
			<xmin>509</xmin>
			<ymin>622</ymin>
			<xmax>652</xmax>
			<ymax>748</ymax>
		</bndbox>
	</object>
	<object>
		<name>window</name>
		<pose>Unspecified</pose>
		<truncated>0</truncated>
		<difficult>0</difficult>
		<bndbox>
			<xmin>160</xmin>
			<ymin>10</ymin>
			<xmax>265</xmax>
			<ymax>41</ymax>
		</bndbox>
	</object>
	<object>
		<name>window</name>
		<pose>Unspecified</pose>
		<truncated>0</truncated>
		<difficult>0</difficult>
		<bndbox>
			<xmin>274</xmin>
			<ymin>11</ymin>
			<xmax>365</xmax>
			<ymax>37</ymax>
		</bndbox>
	</object>
	<object>
		<name>window</name>
		<pose>Unspecified</pose>
		<truncated>0</truncated>
		<difficult>0</difficult>
		<bndbox>
			<xmin>526</xmin>
			<ymin>134</ymin>
			<xmax>631</xmax>
			<ymax>168</ymax>
		</bndbox>
	</object>
	<object>
		<name>window</name>
		<pose>Unspecified</pose>
		<truncated>0</truncated>
		<difficult>0</difficult>
		<bndbox>
			<xmin>721</xmin>
			<ymin>135</ymin>
			<xmax>821</xmax>
			<ymax>168</ymax>
		</bndbox>
	</object>
	<object>
		<name>window</name>
		<pose>Unspecified</pose>
		<truncated>0</truncated>
		<difficult>0</difficult>
		<bndbox>
			<xmin>846</xmin>
			<ymin>176</ymin>
			<xmax>874</xmax>
			<ymax>275</ymax>
		</bndbox>
	</object>
	<object>
		<name>window</name>
		<pose>Unspecified</pose>
		<truncated>0</truncated>
		<difficult>0</difficult>
		<bndbox>
			<xmin>136</xmin>
			<ymin>403</ymin>
			<xmax>159</xmax>
			<ymax>499</ymax>
		</bndbox>
	</object>
	<object>
		<name>door</name>
		<pose>Unspecified</pose>
		<truncated>0</truncated>
		<difficult>0</difficult>
		<bndbox>
			<xmin>505</xmin>
			<ymin>279</ymin>
			<xmax>563</xmax>
			<ymax>340</ymax>
		</bndbox>
	</object>
	<object>
		<name>door</name>
		<pose>Unspecified</pose>
		<truncated>0</truncated>
		<difficult>0</difficult>
		<bndbox>
			<xmin>545</xmin>
			<ymin>519</ymin>
			<xmax>633</xmax>
			<ymax>580</ymax>
		</bndbox>
	</object>
	<object>
		<name>large_sink</name>
		<pose>Unspecified</pose>
		<truncated>0</truncated>
		<difficult>0</difficult>
		<bndbox>
			<xmin>698</xmin>
			<ymin>418</ymin>
			<xmax>736</xmax>
			<ymax>464</ymax>
		</bndbox>
	</object>
	<object>
		<name>small_sink</name>
		<pose>Unspecified</pose>
		<truncated>0</truncated>
		<difficult>0</difficult>
		<bndbox>
			<xmin>732</xmin>
			<ymin>429</ymin>
			<xmax>802</xmax>
			<ymax>464</ymax>
		</bndbox>
	</object>
	<object>
		<name>window</name>
		<pose>Unspecified</pose>
		<truncated>0</truncated>
		<difficult>0</difficult>
		<bndbox>
			<xmin>702</xmin>
			<ymin>557</ymin>
			<xmax>804</xmax>
			<ymax>578</ymax>
		</bndbox>
	</object>
</annotation>
