<annotation>
	<folder>D1_new</folder>
	<filename>110046.gif</filename>
	<path>/media/matrix/Data/data_new/D1_new/110046.gif</path>
	<source>
		<database>Unknown</database>
	</source>
	<size>
		<width>500</width>
		<height>309</height>
		<depth>3</depth>
	</size>
	<segmented>0</segmented>
	<object>
		<name>bed</name>
		<pose>Unspecified</pose>
		<truncated>0</truncated>
		<difficult>0</difficult>
		<bndbox>
			<xmin>12</xmin>
			<ymin>70</ymin>
			<xmax>122</xmax>
			<ymax>127</ymax>
		</bndbox>
	</object>
	<object>
		<name>bed</name>
		<pose>Unspecified</pose>
		<truncated>0</truncated>
		<difficult>0</difficult>
		<bndbox>
			<xmin>13</xmin>
			<ymin>181</ymin>
			<xmax>123</xmax>
			<ymax>238</ymax>
		</bndbox>
	</object>
	<object>
		<name>bed</name>
		<pose>Unspecified</pose>
		<truncated>0</truncated>
		<difficult>0</difficult>
		<bndbox>
			<xmin>367</xmin>
			<ymin>155</ymin>
			<xmax>480</xmax>
			<ymax>241</ymax>
		</bndbox>
	</object>
	<object>
		<name>stairs</name>
		<pose>Unspecified</pose>
		<truncated>0</truncated>
		<difficult>0</difficult>
		<bndbox>
			<xmin>129</xmin>
			<ymin>142</ymin>
			<xmax>166</xmax>
			<ymax>167</ymax>
		</bndbox>
	</object>
	<object>
		<name>stairs</name>
		<pose>Unspecified</pose>
		<truncated>0</truncated>
		<difficult>0</difficult>
		<bndbox>
			<xmin>326</xmin>
			<ymin>99</ymin>
			<xmax>360</xmax>
			<ymax>127</ymax>
		</bndbox>
	</object>
	<object>
		<name>window</name>
		<pose>Unspecified</pose>
		<truncated>0</truncated>
		<difficult>0</difficult>
		<bndbox>
			<xmin>2</xmin>
			<ymin>132</ymin>
			<xmax>13</xmax>
			<ymax>177</ymax>
		</bndbox>
	</object>
	<object>
		<name>window</name>
		<pose>Unspecified</pose>
		<truncated>0</truncated>
		<difficult>0</difficult>
		<bndbox>
			<xmin>480</xmin>
			<ymin>133</ymin>
			<xmax>491</xmax>
			<ymax>178</ymax>
		</bndbox>
	</object>
	<object>
		<name>window</name>
		<pose>Unspecified</pose>
		<truncated>1</truncated>
		<difficult>0</difficult>
		<bndbox>
			<xmin>213</xmin>
			<ymin>296</ymin>
			<xmax>280</xmax>
			<ymax>309</ymax>
		</bndbox>
	</object>
</annotation>
