<annotation>
	<folder>D1_new</folder>
	<filename>117502.gif</filename>
	<path>/media/matrix/Data/data_new/D1_new/117502.gif</path>
	<source>
		<database>Unknown</database>
	</source>
	<size>
		<width>334</width>
		<height>265</height>
		<depth>3</depth>
	</size>
	<segmented>0</segmented>
	<object>
		<name>stairs</name>
		<pose>Unspecified</pose>
		<truncated>0</truncated>
		<difficult>0</difficult>
		<bndbox>
			<xmin>211</xmin>
			<ymin>70</ymin>
			<xmax>240</xmax>
			<ymax>146</ymax>
		</bndbox>
	</object>
	<object>
		<name>door</name>
		<pose>Unspecified</pose>
		<truncated>0</truncated>
		<difficult>0</difficult>
		<bndbox>
			<xmin>247</xmin>
			<ymin>58</ymin>
			<xmax>268</xmax>
			<ymax>75</ymax>
		</bndbox>
	</object>
	<object>
		<name>door</name>
		<pose>Unspecified</pose>
		<truncated>0</truncated>
		<difficult>0</difficult>
		<bndbox>
			<xmin>213</xmin>
			<ymin>147</ymin>
			<xmax>235</xmax>
			<ymax>170</ymax>
		</bndbox>
	</object>
	<object>
		<name>door</name>
		<pose>Unspecified</pose>
		<truncated>0</truncated>
		<difficult>0</difficult>
		<bndbox>
			<xmin>123</xmin>
			<ymin>82</ymin>
			<xmax>144</xmax>
			<ymax>101</ymax>
		</bndbox>
	</object>
	<object>
		<name>door</name>
		<pose>Unspecified</pose>
		<truncated>0</truncated>
		<difficult>0</difficult>
		<bndbox>
			<xmin>67</xmin>
			<ymin>92</ymin>
			<xmax>89</xmax>
			<ymax>106</ymax>
		</bndbox>
	</object>
	<object>
		<name>door</name>
		<pose>Unspecified</pose>
		<truncated>0</truncated>
		<difficult>0</difficult>
		<bndbox>
			<xmin>66</xmin>
			<ymin>135</ymin>
			<xmax>88</xmax>
			<ymax>148</ymax>
		</bndbox>
	</object>
	<object>
		<name>door</name>
		<pose>Unspecified</pose>
		<truncated>0</truncated>
		<difficult>0</difficult>
		<bndbox>
			<xmin>124</xmin>
			<ymin>153</ymin>
			<xmax>147</xmax>
			<ymax>172</ymax>
		</bndbox>
	</object>
	<object>
		<name>door</name>
		<pose>Unspecified</pose>
		<truncated>0</truncated>
		<difficult>0</difficult>
		<bndbox>
			<xmin>149</xmin>
			<ymin>175</ymin>
			<xmax>173</xmax>
			<ymax>189</ymax>
		</bndbox>
	</object>
	<object>
		<name>door</name>
		<pose>Unspecified</pose>
		<truncated>0</truncated>
		<difficult>0</difficult>
		<bndbox>
			<xmin>271</xmin>
			<ymin>128</ymin>
			<xmax>289</xmax>
			<ymax>148</ymax>
		</bndbox>
	</object>
	<object>
		<name>door</name>
		<pose>Unspecified</pose>
		<truncated>0</truncated>
		<difficult>0</difficult>
		<bndbox>
			<xmin>288</xmin>
			<ymin>102</ymin>
			<xmax>302</xmax>
			<ymax>117</ymax>
		</bndbox>
	</object>
	<object>
		<name>door</name>
		<pose>Unspecified</pose>
		<truncated>0</truncated>
		<difficult>0</difficult>
		<bndbox>
			<xmin>128</xmin>
			<ymin>120</ymin>
			<xmax>144</xmax>
			<ymax>134</ymax>
		</bndbox>
	</object>
	<object>
		<name>door</name>
		<pose>Unspecified</pose>
		<truncated>0</truncated>
		<difficult>0</difficult>
		<bndbox>
			<xmin>109</xmin>
			<ymin>136</ymin>
			<xmax>123</xmax>
			<ymax>151</ymax>
		</bndbox>
	</object>
	<object>
		<name>tub</name>
		<pose>Unspecified</pose>
		<truncated>0</truncated>
		<difficult>0</difficult>
		<bndbox>
			<xmin>92</xmin>
			<ymin>104</ymin>
			<xmax>109</xmax>
			<ymax>136</ymax>
		</bndbox>
	</object>
	<object>
		<name>large_sink</name>
		<pose>Unspecified</pose>
		<truncated>0</truncated>
		<difficult>0</difficult>
		<bndbox>
			<xmin>109</xmin>
			<ymin>106</ymin>
			<xmax>122</xmax>
			<ymax>120</ymax>
		</bndbox>
	</object>
	<object>
		<name>large_sink</name>
		<pose>Unspecified</pose>
		<truncated>0</truncated>
		<difficult>0</difficult>
		<bndbox>
			<xmin>258</xmin>
			<ymin>103</ymin>
			<xmax>274</xmax>
			<ymax>120</ymax>
		</bndbox>
	</object>
	<object>
		<name>tub</name>
		<pose>Unspecified</pose>
		<truncated>0</truncated>
		<difficult>0</difficult>
		<bndbox>
			<xmin>242</xmin>
			<ymin>113</ymin>
			<xmax>257</xmax>
			<ymax>142</ymax>
		</bndbox>
	</object>
	<object>
		<name>small_sink</name>
		<pose>Unspecified</pose>
		<truncated>0</truncated>
		<difficult>0</difficult>
		<bndbox>
			<xmin>307</xmin>
			<ymin>115</ymin>
			<xmax>321</xmax>
			<ymax>143</ymax>
		</bndbox>
	</object>
	<object>
		<name>window</name>
		<pose>Unspecified</pose>
		<truncated>0</truncated>
		<difficult>0</difficult>
		<bndbox>
			<xmin>75</xmin>
			<ymin>13</ymin>
			<xmax>95</xmax>
			<ymax>20</ymax>
		</bndbox>
	</object>
	<object>
		<name>window</name>
		<pose>Unspecified</pose>
		<truncated>0</truncated>
		<difficult>0</difficult>
		<bndbox>
			<xmin>151</xmin>
			<ymin>13</ymin>
			<xmax>188</xmax>
			<ymax>21</ymax>
		</bndbox>
	</object>
	<object>
		<name>window</name>
		<pose>Unspecified</pose>
		<truncated>0</truncated>
		<difficult>0</difficult>
		<bndbox>
			<xmin>89</xmin>
			<ymin>217</ymin>
			<xmax>127</xmax>
			<ymax>225</ymax>
		</bndbox>
	</object>
	<object>
		<name>window</name>
		<pose>Unspecified</pose>
		<truncated>0</truncated>
		<difficult>0</difficult>
		<bndbox>
			<xmin>7</xmin>
			<ymin>67</ymin>
			<xmax>14</xmax>
			<ymax>106</ymax>
		</bndbox>
	</object>
	<object>
		<name>window</name>
		<pose>Unspecified</pose>
		<truncated>0</truncated>
		<difficult>0</difficult>
		<bndbox>
			<xmin>242</xmin>
			<ymin>244</ymin>
			<xmax>294</xmax>
			<ymax>250</ymax>
		</bndbox>
	</object>
	<object>
		<name>window</name>
		<pose>Unspecified</pose>
		<truncated>0</truncated>
		<difficult>0</difficult>
		<bndbox>
			<xmin>12</xmin>
			<ymin>186</ymin>
			<xmax>29</xmax>
			<ymax>203</ymax>
		</bndbox>
	</object>
	<object>
		<name>window</name>
		<pose>Unspecified</pose>
		<truncated>0</truncated>
		<difficult>0</difficult>
		<bndbox>
			<xmin>10</xmin>
			<ymin>208</ymin>
			<xmax>17</xmax>
			<ymax>226</ymax>
		</bndbox>
	</object>
	<object>
		<name>window</name>
		<pose>Unspecified</pose>
		<truncated>0</truncated>
		<difficult>0</difficult>
		<bndbox>
			<xmin>14</xmin>
			<ymin>229</ymin>
			<xmax>29</xmax>
			<ymax>246</ymax>
		</bndbox>
	</object>
	<object>
		<name>window</name>
		<pose>Unspecified</pose>
		<truncated>0</truncated>
		<difficult>0</difficult>
		<bndbox>
			<xmin>34</xmin>
			<ymin>244</ymin>
			<xmax>53</xmax>
			<ymax>252</ymax>
		</bndbox>
	</object>
	<object>
		<name>window</name>
		<pose>Unspecified</pose>
		<truncated>0</truncated>
		<difficult>0</difficult>
		<bndbox>
			<xmin>60</xmin>
			<ymin>232</ymin>
			<xmax>73</xmax>
			<ymax>246</ymax>
		</bndbox>
	</object>
</annotation>
