<annotation>
	<folder>D1_new</folder>
	<filename>12331.gif</filename>
	<path>G:/data_new/D1_new/12331.gif</path>
	<source>
		<database>Unknown</database>
	</source>
	<size>
		<width>600</width>
		<height>740</height>
		<depth>3</depth>
	</size>
	<segmented>0</segmented>
	<object>
		<name>stairs</name>
		<pose>Unspecified</pose>
		<truncated>0</truncated>
		<difficult>0</difficult>
		<bndbox>
			<xmin>405</xmin>
			<ymin>307</ymin>
			<xmax>532</xmax>
			<ymax>449</ymax>
		</bndbox>
	</object>
	<object>
		<name>stairs</name>
		<pose>Unspecified</pose>
		<truncated>0</truncated>
		<difficult>0</difficult>
		<bndbox>
			<xmin>2</xmin>
			<ymin>342</ymin>
			<xmax>66</xmax>
			<ymax>417</ymax>
		</bndbox>
	</object>
	<object>
		<name>door</name>
		<pose>Unspecified</pose>
		<truncated>0</truncated>
		<difficult>0</difficult>
		<bndbox>
			<xmin>158</xmin>
			<ymin>325</ymin>
			<xmax>211</xmax>
			<ymax>429</ymax>
		</bndbox>
	</object>
	<object>
		<name>door</name>
		<pose>Unspecified</pose>
		<truncated>0</truncated>
		<difficult>0</difficult>
		<bndbox>
			<xmin>344</xmin>
			<ymin>48</ymin>
			<xmax>399</xmax>
			<ymax>103</ymax>
		</bndbox>
	</object>
	<object>
		<name>door</name>
		<pose>Unspecified</pose>
		<truncated>0</truncated>
		<difficult>0</difficult>
		<bndbox>
			<xmin>346</xmin>
			<ymin>104</ymin>
			<xmax>400</xmax>
			<ymax>157</ymax>
		</bndbox>
	</object>
	<object>
		<name>door</name>
		<pose>Unspecified</pose>
		<truncated>0</truncated>
		<difficult>0</difficult>
		<bndbox>
			<xmin>377</xmin>
			<ymin>565</ymin>
			<xmax>438</xmax>
			<ymax>622</ymax>
		</bndbox>
	</object>
	<object>
		<name>door</name>
		<pose>Unspecified</pose>
		<truncated>0</truncated>
		<difficult>0</difficult>
		<bndbox>
			<xmin>440</xmin>
			<ymin>569</ymin>
			<xmax>495</xmax>
			<ymax>625</ymax>
		</bndbox>
	</object>
	<object>
		<name>door</name>
		<pose>Unspecified</pose>
		<truncated>0</truncated>
		<difficult>0</difficult>
		<bndbox>
			<xmin>341</xmin>
			<ymin>634</ymin>
			<xmax>379</xmax>
			<ymax>708</ymax>
		</bndbox>
	</object>
	<object>
		<name>windows</name>
		<pose>Unspecified</pose>
		<truncated>0</truncated>
		<difficult>0</difficult>
		<bndbox>
			<xmin>93</xmin>
			<ymin>710</ymin>
			<xmax>261</xmax>
			<ymax>732</ymax>
		</bndbox>
	</object>
	<object>
		<name>windows</name>
		<pose>Unspecified</pose>
		<truncated>0</truncated>
		<difficult>0</difficult>
		<bndbox>
			<xmin>59</xmin>
			<ymin>526</ymin>
			<xmax>79</xmax>
			<ymax>701</ymax>
		</bndbox>
	</object>
	<object>
		<name>windows</name>
		<pose>Unspecified</pose>
		<truncated>0</truncated>
		<difficult>0</difficult>
		<bndbox>
			<xmin>84</xmin>
			<ymin>446</ymin>
			<xmax>185</xmax>
			<ymax>466</ymax>
		</bndbox>
	</object>
	<object>
		<name>door</name>
		<pose>Unspecified</pose>
		<truncated>0</truncated>
		<difficult>0</difficult>
		<bndbox>
			<xmin>441</xmin>
			<ymin>191</ymin>
			<xmax>494</xmax>
			<ymax>246</ymax>
		</bndbox>
	</object>
	<object>
		<name>windows</name>
		<pose>Unspecified</pose>
		<truncated>0</truncated>
		<difficult>0</difficult>
		<bndbox>
			<xmin>524</xmin>
			<ymin>156</ymin>
			<xmax>546</xmax>
			<ymax>240</ymax>
		</bndbox>
	</object>
	<object>
		<name>windows</name>
		<pose>Unspecified</pose>
		<truncated>0</truncated>
		<difficult>0</difficult>
		<bndbox>
			<xmin>207</xmin>
			<ymin>115</ymin>
			<xmax>224</xmax>
			<ymax>294</ymax>
		</bndbox>
	</object>
	<object>
		<name>twin_sink</name>
		<pose>Unspecified</pose>
		<truncated>0</truncated>
		<difficult>0</difficult>
		<bndbox>
			<xmin>217</xmin>
			<ymin>151</ymin>
			<xmax>253</xmax>
			<ymax>208</ymax>
		</bndbox>
	</object>
	<object>
		<name>dining_table</name>
		<pose>Unspecified</pose>
		<truncated>0</truncated>
		<difficult>0</difficult>
		<bndbox>
			<xmin>96</xmin>
			<ymin>133</ymin>
			<xmax>181</xmax>
			<ymax>222</ymax>
		</bndbox>
	</object>
	<object>
		<name>large_sink</name>
		<pose>Unspecified</pose>
		<truncated>0</truncated>
		<difficult>0</difficult>
		<bndbox>
			<xmin>456</xmin>
			<ymin>108</ymin>
			<xmax>489</xmax>
			<ymax>152</ymax>
		</bndbox>
	</object>
	<object>
		<name>small_sink</name>
		<pose>Unspecified</pose>
		<truncated>0</truncated>
		<difficult>0</difficult>
		<bndbox>
			<xmin>491</xmin>
			<ymin>104</ymin>
			<xmax>534</xmax>
			<ymax>141</ymax>
		</bndbox>
	</object>
	<object>
		<name>windows</name>
		<pose>Unspecified</pose>
		<truncated>0</truncated>
		<difficult>0</difficult>
		<bndbox>
			<xmin>451</xmin>
			<ymin>532</ymin>
			<xmax>496</xmax>
			<ymax>551</ymax>
		</bndbox>
	</object>
	<object>
		<name>dining_table</name>
		<pose>Unspecified</pose>
		<truncated>0</truncated>
		<difficult>0</difficult>
		<bndbox>
			<xmin>236</xmin>
			<ymin>333</ymin>
			<xmax>360</xmax>
			<ymax>423</ymax>
		</bndbox>
	</object>
</annotation>
