<annotation>
	<folder>D1_new</folder>
	<filename>125111.gif</filename>
	<path>/media/matrix/Data/data_new/D1_new/125111.gif</path>
	<source>
		<database>Unknown</database>
	</source>
	<size>
		<width>367</width>
		<height>495</height>
		<depth>3</depth>
	</size>
	<segmented>0</segmented>
	<object>
		<name>stairs</name>
		<pose>Unspecified</pose>
		<truncated>0</truncated>
		<difficult>0</difficult>
		<bndbox>
			<xmin>167</xmin>
			<ymin>178</ymin>
			<xmax>285</xmax>
			<ymax>231</ymax>
		</bndbox>
	</object>
	<object>
		<name>door</name>
		<pose>Unspecified</pose>
		<truncated>0</truncated>
		<difficult>0</difficult>
		<bndbox>
			<xmin>140</xmin>
			<ymin>107</ymin>
			<xmax>165</xmax>
			<ymax>137</ymax>
		</bndbox>
	</object>
	<object>
		<name>door</name>
		<pose>Unspecified</pose>
		<truncated>0</truncated>
		<difficult>0</difficult>
		<bndbox>
			<xmin>167</xmin>
			<ymin>149</ymin>
			<xmax>200</xmax>
			<ymax>176</ymax>
		</bndbox>
	</object>
	<object>
		<name>door</name>
		<pose>Unspecified</pose>
		<truncated>0</truncated>
		<difficult>0</difficult>
		<bndbox>
			<xmin>142</xmin>
			<ymin>180</ymin>
			<xmax>173</xmax>
			<ymax>208</ymax>
		</bndbox>
	</object>
	<object>
		<name>tub</name>
		<pose>Unspecified</pose>
		<truncated>0</truncated>
		<difficult>0</difficult>
		<bndbox>
			<xmin>56</xmin>
			<ymin>66</ymin>
			<xmax>85</xmax>
			<ymax>116</ymax>
		</bndbox>
	</object>
	<object>
		<name>large_sink</name>
		<pose>Unspecified</pose>
		<truncated>0</truncated>
		<difficult>0</difficult>
		<bndbox>
			<xmin>125</xmin>
			<ymin>55</ymin>
			<xmax>148</xmax>
			<ymax>74</ymax>
		</bndbox>
	</object>
	<object>
		<name>small_sink</name>
		<pose>Unspecified</pose>
		<truncated>0</truncated>
		<difficult>0</difficult>
		<bndbox>
			<xmin>82</xmin>
			<ymin>118</ymin>
			<xmax>133</xmax>
			<ymax>135</ymax>
		</bndbox>
	</object>
	<object>
		<name>twin_sink</name>
		<pose>Unspecified</pose>
		<truncated>0</truncated>
		<difficult>0</difficult>
		<bndbox>
			<xmin>56</xmin>
			<ymin>165</ymin>
			<xmax>77</xmax>
			<ymax>193</ymax>
		</bndbox>
	</object>
	<object>
		<name>door</name>
		<pose>Unspecified</pose>
		<truncated>0</truncated>
		<difficult>0</difficult>
		<bndbox>
			<xmin>253</xmin>
			<ymin>234</ymin>
			<xmax>286</xmax>
			<ymax>265</ymax>
		</bndbox>
	</object>
	<object>
		<name>window</name>
		<pose>Unspecified</pose>
		<truncated>0</truncated>
		<difficult>0</difficult>
		<bndbox>
			<xmin>86</xmin>
			<ymin>44</ymin>
			<xmax>133</xmax>
			<ymax>52</ymax>
		</bndbox>
	</object>
	<object>
		<name>window</name>
		<pose>Unspecified</pose>
		<truncated>0</truncated>
		<difficult>0</difficult>
		<bndbox>
			<xmin>207</xmin>
			<ymin>43</ymin>
			<xmax>249</xmax>
			<ymax>52</ymax>
		</bndbox>
	</object>
	<object>
		<name>window</name>
		<pose>Unspecified</pose>
		<truncated>0</truncated>
		<difficult>0</difficult>
		<bndbox>
			<xmin>50</xmin>
			<ymin>284</ymin>
			<xmax>61</xmax>
			<ymax>332</ymax>
		</bndbox>
	</object>
</annotation>
