<annotation>
	<folder>D1_new</folder>
	<filename>15862.gif</filename>
	<path>/media/matrix/Data/data_new/D1_new/15862.gif</path>
	<source>
		<database>Unknown</database>
	</source>
	<size>
		<width>517</width>
		<height>477</height>
		<depth>3</depth>
	</size>
	<segmented>0</segmented>
	<object>
		<name>stairs</name>
		<pose>Unspecified</pose>
		<truncated>0</truncated>
		<difficult>0</difficult>
		<bndbox>
			<xmin>263</xmin>
			<ymin>162</ymin>
			<xmax>351</xmax>
			<ymax>240</ymax>
		</bndbox>
	</object>
	<object>
		<name>door</name>
		<pose>Unspecified</pose>
		<truncated>0</truncated>
		<difficult>0</difficult>
		<bndbox>
			<xmin>91</xmin>
			<ymin>319</ymin>
			<xmax>146</xmax>
			<ymax>364</ymax>
		</bndbox>
	</object>
	<object>
		<name>large_sink</name>
		<pose>Unspecified</pose>
		<truncated>0</truncated>
		<difficult>0</difficult>
		<bndbox>
			<xmin>89</xmin>
			<ymin>370</ymin>
			<xmax>144</xmax>
			<ymax>414</ymax>
		</bndbox>
	</object>
	<object>
		<name>window</name>
		<pose>Unspecified</pose>
		<truncated>0</truncated>
		<difficult>0</difficult>
		<bndbox>
			<xmin>62</xmin>
			<ymin>33</ymin>
			<xmax>135</xmax>
			<ymax>48</ymax>
		</bndbox>
	</object>
	<object>
		<name>window</name>
		<pose>Unspecified</pose>
		<truncated>0</truncated>
		<difficult>0</difficult>
		<bndbox>
			<xmin>63</xmin>
			<ymin>422</ymin>
			<xmax>132</xmax>
			<ymax>438</ymax>
		</bndbox>
	</object>
</annotation>
