<annotation>
	<folder>Region_wise_annotations1</folder>
	<filename>112772.gif</filename>
	<path>/media/matrix/Data/BRIDGE/Region_wise_annotations1/112772.gif</path>
	<source>
		<database>Unknown</database>
	</source>
	<size>
		<width>600</width>
		<height>370</height>
		<depth>3</depth>
	</size>
	<segmented>0</segmented>
	<object>
		<name>livingroom has a large sofa and bed</name>
		<pose>Unspecified</pose>
		<truncated>0</truncated>
		<difficult>0</difficult>
		<bndbox>
			<xmin>243</xmin>
			<ymin>41</ymin>
			<xmax>360</xmax>
			<ymax>160</ymax>
		</bndbox>
	</object>
	<object>
		<name>bedroom has a double bed with	bedside stands</name>
		<pose>Unspecified</pose>
		<truncated>0</truncated>
		<difficult>0</difficult>
		<bndbox>
			<xmin>359</xmin>
			<ymin>117</ymin>
			<xmax>453</xmax>
			<ymax>210</ymax>
		</bndbox>
	</object>
	<object>
		<name>bedroom has a double bed with	bedside stands</name>
		<pose>Unspecified</pose>
		<truncated>0</truncated>
		<difficult>0</difficult>
		<bndbox>
			<xmin>18</xmin>
			<ymin>120</ymin>
			<xmax>117</xmax>
			<ymax>207</ymax>
		</bndbox>
	</object>
	<object>
		<name>bathroom has a bathtub with small and large sink</name>
		<pose>Unspecified</pose>
		<truncated>0</truncated>
		<difficult>0</difficult>
		<bndbox>
			<xmin>121</xmin>
			<ymin>187</ymin>
			<xmax>184</xmax>
			<ymax>264</ymax>
		</bndbox>
	</object>
	<object>
		<name>open area has stairs</name>
		<pose>Unspecified</pose>
		<truncated>0</truncated>
		<difficult>0</difficult>
		<bndbox>
			<xmin>249</xmin>
			<ymin>179</ymin>
			<xmax>345</xmax>
			<ymax>324</ymax>
		</bndbox>
	</object>
</annotation>
