<annotation>
	<folder>D1_densecap</folder>
	<filename>1371.gif</filename>
	<path>G:/data_new/D1_densecap/1371.gif</path>
	<source>
		<database>Unknown</database>
	</source>
	<size>
		<width>600</width>
		<height>440</height>
		<depth>3</depth>
	</size>
	<segmented>0</segmented>
	<object>
		<name>master bedroom has a master bathroom with tub, shower and sink</name>
		<pose>Unspecified</pose>
		<truncated>0</truncated>
		<difficult>0</difficult>
		<bndbox>
			<xmin>58</xmin>
			<ymin>201</ymin>
			<xmax>154</xmax>
			<ymax>408</ymax>
		</bndbox>
	</object>
	<object>
		<name>there is a screened porch with sitting and dining facility</name>
		<pose>Unspecified</pose>
		<truncated>0</truncated>
		<difficult>0</difficult>
		<bndbox>
			<xmin>286</xmin>
			<ymin>43</ymin>
			<xmax>393</xmax>
			<ymax>124</ymax>
		</bndbox>
	</object>
	<object>
		<name>great room has sofas and tables for sitting and dining</name>
		<pose>Unspecified</pose>
		<truncated>0</truncated>
		<difficult>0</difficult>
		<bndbox>
			<xmin>140</xmin>
			<ymin>124</ymin>
			<xmax>253</xmax>
			<ymax>208</ymax>
		</bndbox>
	</object>
	<object>
		<name>kitchen has a kitchen island, dining table, and other cooking and dining facilities</name>
		<pose>Unspecified</pose>
		<truncated>0</truncated>
		<difficult>0</difficult>
		<bndbox>
			<xmin>245</xmin>
			<ymin>122</ymin>
			<xmax>347</xmax>
			<ymax>281</ymax>
		</bndbox>
	</object>
	<object>
		<name>sunroom has sitting facility outside</name>
		<pose>Unspecified</pose>
		<truncated>0</truncated>
		<difficult>0</difficult>
		<bndbox>
			<xmin>57</xmin>
			<ymin>121</ymin>
			<xmax>141</xmax>
			<ymax>200</ymax>
		</bndbox>
	</object>
	<object>
		<name>there is a bedroom near entry which has a double bed and sofa</name>
		<pose>Unspecified</pose>
		<truncated>0</truncated>
		<difficult>0</difficult>
		<bndbox>
			<xmin>232</xmin>
			<ymin>272</ymin>
			<xmax>349</xmax>
			<ymax>412</ymax>
		</bndbox>
	</object>
</annotation>
